hep_spt/__init__.py
hep_spt/adbin.py
hep_spt/cls.py
hep_spt/core.py
hep_spt/math_aux.py
hep_spt/plotting.py
hep_spt/stats.py
hep_spt/version.py
hep_spt/data/poisson_fu.dat
hep_spt/data/poisson_llu.dat
hep_spt/mpl/default.mplstyle
hep_spt/mpl/multiplot.mplstyle
hep_spt/mpl/singleplot.mplstyle
hep_spt-0.0.0.dev2.dist-info/DESCRIPTION.rst
hep_spt-0.0.0.dev2.dist-info/METADATA
hep_spt-0.0.0.dev2.dist-info/RECORD
hep_spt-0.0.0.dev2.dist-info/WHEEL
hep_spt-0.0.0.dev2.dist-info/metadata.json
hep_spt-0.0.0.dev2.dist-info/top_level.txt
