Metadata-Version: 2.0
Name: hep-spt
Version: 0.0.0.dev2
Summary: Provides statistical and plotting tools using general python packages, focused to High Energy Physics.
Home-page: UNKNOWN
Author: UNKNOWN
Author-email: UNKNOWN
License: UNKNOWN
Keywords: physics hep statistics plotting
Platform: UNKNOWN
Requires-Dist: matplotlib
Requires-Dist: numpy
Requires-Dist: pytest
Requires-Dist: scipy
